la_env-0.1.0.dist-info/METADATA
la_env-0.1.0.dist-info/WHEEL
la_env/__init__.py
la_env-0.1.0.dist-info/RECORD
