Metadata-Version: 2.1
Name: la-env
Version: 0.1.0
Summary: Check environment variables
Author-Email: thiagola92 <thiagola92@gmail.com>
License: MIT
Requires-Python: >=3.11
